[{"name":"com.bandoware.gameplaytags","repoUrl":"https://github.com/BandoWare/GameplayTags","displayName":"Gameplay Tags","description":"A package to manage gameplay tags for your game.","licenseSpdxId":"","licenseName":"MIT","topics":["data-management"],"hunter":"felipemcoliveira","createdAt":1725802972782,"image":"","parentRepoUrl":null,"readme":"release/0.1.0-beta.4:README.md","gitTagPrefix":"","gitTagIgnore":"","minVersion":"","imageFit":"cover","repo":"GameplayTags","owner":"BandoWare","ownerUrl":"https://github.com/BandoWare","parentRepo":null,"parentOwner":null,"parentOwnerUrl":null,"readmeBranch":"release/0.1.0-beta.4","hunterUrl":"https://github.com/felipemcoliveira"}]