[{"name":"com.esotericsoftware.spine.spine-csharp","repoUrl":"https://github.com/EsotericSoftware/spine-runtimes","displayName":"spine-csharp Runtime","description":"This plugin provides the spine-csharp core runtime.","licenseSpdxId":"","licenseName":"SEE LICENSE IN LICENSE","topics":["2d","animation"],"hunter":"The1Studio","createdAt":1715518294788,"image":"","parentRepoUrl":null,"readme":"4.2:README.md","gitTagPrefix":"","gitTagIgnore":"","minVersion":"","imageFit":"cover","repo":"spine-runtimes","owner":"EsotericSoftware","ownerUrl":"https://github.com/EsotericSoftware","parentRepo":null,"parentOwner":null,"parentOwnerUrl":null,"readmeBranch":"4.2","hunterUrl":"https://github.com/The1Studio"}]