[{"name":"com.alpha.fmstream","repoUrl":"https://github.com/dgthomugo/drag","displayName":"fmstream","description":"fmstream","licenseSpdxId":"MIT","licenseName":"MIT License","topics":["ar-and-vr"],"hunter":"dgthomugo","createdAt":1719576242752,"image":"","parentRepoUrl":null,"readme":"main:README.md","gitTagPrefix":"","gitTagIgnore":"","minVersion":"","imageFit":"cover","repo":"drag","owner":"dgthomugo","ownerUrl":"https://github.com/dgthomugo","parentRepo":null,"parentOwner":null,"parentOwnerUrl":null,"readmeBranch":"main","hunterUrl":"https://github.com/dgthomugo"}]